shield34-reporter-tests/__init__.py
shield34-reporter-tests/reporter-tests/__init__.py
shield34-reporter-tests/reporter-tests/externalkeywords/__init__.py
shield34-reporter-tests/reporter-tests/externalkeywords/userkeywords.py
shield34-reporter-tests/reporter-tests/resources/__init__.py
shield34-reporter-tests/reporter-tests/resources/blockrunstep.py
shield34-reporter-tests/reporter-tests/resources/configuration.py
shield34-reporter-tests/reporter-tests/resources/connection.py
shield34-reporter-tests/reporter-tests/resources/run_block_container_connection.py
shield34_reporter/__init__.py
shield34_reporter/auth/__init__.py
shield34_reporter/auth/authorization_info.py
shield34_reporter/auth/basic_proxy_authentication.py
shield34_reporter/auth/kerberos_proxy_authentication.py
shield34_reporter/auth/ntlm_proxy_authentication.py
shield34_reporter/auth/proxy_authentication.py
shield34_reporter/auth/sdk_authentication.py
shield34_reporter/consts/__init__.py
shield34_reporter/consts/js_consts.py
shield34_reporter/consts/shield34_properties.py
shield34_reporter/consts/shield34_properties_constants.py
shield34_reporter/container/__init__.py
shield34_reporter/container/block_run_report_container.py
shield34_reporter/container/run_report_container.py
shield34_reporter/dynamic_locator/__init__.py
shield34_reporter/dynamic_locator/element_dynamic_locator.py
shield34_reporter/exceptions/__init__.py
shield34_reporter/handler/__init__.py
shield34_reporter/handler/action_chains.py
shield34_reporter/handler/web_driver.py
shield34_reporter/handler/web_driver_wait.py
shield34_reporter/handler/web_element.py
shield34_reporter/helpers/__init__.py
shield34_reporter/helpers/web_element_helper.py
shield34_reporter/listeners/__init__.py
shield34_reporter/listeners/behave_listener.py
shield34_reporter/listeners/enum_encoder.py
shield34_reporter/listeners/listener_utils.py
shield34_reporter/listeners/robot_listener.py
shield34_reporter/listeners/shield34_listener.py
shield34-1.0.408.dist-info/METADATA
shield34-1.0.408.dist-info/WHEEL
shield34-1.0.408.dist-info/entry_points.txt
shield34-1.0.408.dist-info/top_level.txt
shield34-1.0.408.dist-info/RECORD
