Metadata-Version: 2.1
Name: shield34
Version: 1.0.408
Summary: Python client for Shield34, an AI-based solution for Selenium coders who want to keep using Selenium while enjoying stability, deep analysis and much shorter test runs.
Home-page: https://www.shield34.com
Author: Shield34
Author-email: support@shield34.com
License: UNKNOWN
Keywords: shield34 Robot Selenium AI stability RCA analysis
Platform: UNKNOWN
Classifier: Programming Language :: Python
Classifier: Programming Language :: Python :: 3
Classifier: Programming Language :: Python :: 3.5
Classifier: Programming Language :: Python :: 3.6
Classifier: Programming Language :: Python :: 3.7
Classifier: Framework :: Pytest
Requires-Python: >=2.6
Requires-Dist: requests
Requires-Dist: urllib3
Requires-Dist: configparser
Requires-Dist: unicodecsv
Requires-Dist: enum34
Requires-Dist: futures
